pvrecorderdemo/LICENSE
pvrecorderdemo/pv_recorder_demo.py
pvrecorderdemo-1.2.8.dist-info/METADATA
pvrecorderdemo-1.2.8.dist-info/WHEEL
pvrecorderdemo-1.2.8.dist-info/entry_points.txt
pvrecorderdemo-1.2.8.dist-info/top_level.txt
pvrecorderdemo-1.2.8.dist-info/RECORD
