Metadata-Version: 2.1
Name: pvrecorderdemo
Version: 1.2.8
Summary: Recorder library for Picovoice.
Home-page: https://github.com/Picovoice/pvrecorder
Author: Picovoice
Author-email: hello@picovoice.ai
Keywords: Audio Recorder
Classifier: Development Status :: 5 - Production/Stable
Classifier: Intended Audience :: Developers
Classifier: License :: OSI Approved :: Apache Software License
Classifier: Operating System :: OS Independent
Classifier: Programming Language :: Python :: 3
Classifier: Topic :: Multimedia :: Sound/Audio :: Speech
Requires-Python: >=3.9
Requires-Dist: pvrecorder==1.2.7
